supertype/__init__.py
supertype/supertype.py
supertype-python/__init__.py
supertype-python/supertype-python.py
supertype-python/supertype.py
supertype_python/__init__.py
supertype_python/supertype_python.py
supertype_python-1.1.0.dist-info/LICENSE
supertype_python-1.1.0.dist-info/METADATA
supertype_python-1.1.0.dist-info/WHEEL
supertype_python-1.1.0.dist-info/top_level.txt
supertype_python-1.1.0.dist-info/RECORD
